[
  {
    "username": "Khan",
    "message": "Hello guys",
    "time": "15:21:42",
    "sender": "Khan"
  },
  {
    "username": "Khan",
    "message": "H",
    "time": "15:21:47",
    "sender": "Khan"
  },
  {
    "username": "Ui",
    "message": "H",
    "time": "15:22:26",
    "sender": "Ui"
  },
  {
    "username": "Ui",
    "message": "ن",
    "time": "15:23:44",
    "sender": "Ui"
  },
  {
    "username": "Khan",
    "message": "ع",
    "time": "15:23:46",
    "sender": "Khan"
  },
  {
    "username": "Op",
    "message": "Hh",
    "time": "15:30:54",
    "sender": "Op"
  },
  {
    "username": "Amir",
    "message": "Hii",
    "time": "15:38:42",
    "sender": "Amir"
  },
  {
    "username": "Amir",
    "message": "H",
    "time": "15:39:22",
    "sender": "Amir"
  },
  {
    "username": "Amir",
    "message": "Hii",
    "time": "15:39:24",
    "sender": "Amir"
  }
]